nonebot_plugin_nailongkiller/__init__.py
nonebot_plugin_nailongkiller/config.py
nonebot_plugin_nailongkiller/frame_source.py
nonebot_plugin_nailongkiller/handler.py
nonebot_plugin_nailongkiller/model/__init__.py
nonebot_plugin_nailongkiller/model/classification.py
nonebot_plugin_nailongkiller/model/hf_inference.py
nonebot_plugin_nailongkiller/model/target_detection.py
nonebot_plugin_nailongkiller/model/utils/__init__.py
nonebot_plugin_nailongkiller/model/utils/common.py
nonebot_plugin_nailongkiller/model/utils/update.py
nonebot_plugin_nailongkiller/uniapi/__init__.py
nonebot_plugin_nailongkiller/uniapi/mute.py
nonebot_plugin_nailongkiller/uniapi/recall.py
nonebot_plugin_nailongkiller_base-2.3.1.post1.dist-info/METADATA
nonebot_plugin_nailongkiller_base-2.3.1.post1.dist-info/WHEEL
nonebot_plugin_nailongkiller_base-2.3.1.post1.dist-info/entry_points.txt
nonebot_plugin_nailongkiller_base-2.3.1.post1.dist-info/RECORD
