Metadata-Version: 2.1
Name: nonebot-plugin-nailongkiller-base
Version: 2.3.1.post1
Summary: 识别目标并撤回图片插件
Keywords: nonebot,plugin,image
Author-Email: 445 <2877834692@qq.com>, student_2333 <lgc2333@126.com>
License: MIT
Project-URL: homepage, https://github.com/Hakureirm/nonebot-plugin-nailongkiller
Project-URL: repository, https://github.com/Hakureirm/nonebot-plugin-nailongkiller
Requires-Python: <4.0,>=3.9
Requires-Dist: nonebot2>=2.2.0
Requires-Dist: nonebot-plugin-alconna>=0.53.1
Requires-Dist: nonebot-plugin-uninfo>=0.5.0
Requires-Dist: opencv-python>=4.5
Requires-Dist: numpy>=1.19
Requires-Dist: keras>=2.4
Requires-Dist: pillow>=9
Requires-Dist: cookit[pydantic]>=0.8.1
Requires-Dist: httpx>=0.27.2
Requires-Dist: githubkit>=0.11.14
Requires-Dist: yarl>=1.17.1
Requires-Dist: tqdm>=4.66.6
Requires-Dist: ultralytics>=8.0.0
Provides-Extra: model0
Requires-Dist: tensorflow>=2.4; extra == "model0"
Provides-Extra: model1
Requires-Dist: ultralytics>=8.0.0; extra == "model1"
Requires-Dist: torch>=2.0.0; extra == "model1"
Provides-Extra: hf
Requires-Dist: gradio-client>=1.7.1; extra == "hf"
Provides-Extra: all
Requires-Dist: tensorflow>=2.4; extra == "all"
Requires-Dist: ultralytics>=8.0.0; extra == "all"
Requires-Dist: torch>=2.0.0; extra == "all"
Requires-Dist: gradio-client>=1.7.1; extra == "all"
